tensorlens/__init__.py
tensorlens/tensorlens.py
tensorlens/core/__init__.py
tensorlens/core/global_store.py
tensorlens/web/__init__.py
tensorlens/web/server.py
tensorlens/web/static/index.html
tensorlens/web/static/assets/index-b209e0d7.js
tensorlens-0.0.3.dist-info/licenses/LICENSE
tensorlens-0.0.3.dist-info/METADATA
tensorlens-0.0.3.dist-info/WHEEL
tensorlens-0.0.3.dist-info/entry_points.txt
tensorlens-0.0.3.dist-info/top_level.txt
tensorlens-0.0.3.dist-info/RECORD
