Metadata-Version: 2.4
Name: tensorlens
Version: 0.0.3
Summary: tensorlens
Author-email: attentionmech <attentionmech@gmail.com>
License: MIT
License-File: LICENSE
Requires-Dist: flask
Requires-Dist: gunicorn
Requires-Dist: ipython
Requires-Dist: numpy
Dynamic: license-file
